django_config/__init__.py
django_config/admin.py
django_config/apps.py
django_config/models.py
django_config/tests.py
django_config/views.py
django_config/migrations/0001_initial.py
django_config/migrations/0002_config_property_property_type.py
django_config/migrations/0003_auto_20220125_1213.py
django_config/migrations/__init__.py
django_config/models/__init__.py
django_config/models/abstract_config_property.py
django_config/models/config_property.py
django_config/south_migrations/0001_initial.py
django_config/south_migrations/__init__.py
django_basic_config-1.1.0.dist-info/LICENSE
django_basic_config-1.1.0.dist-info/METADATA
django_basic_config-1.1.0.dist-info/WHEEL
django_basic_config-1.1.0.dist-info/top_level.txt
django_basic_config-1.1.0.dist-info/RECORD
