Metadata-Version: 2.1
Name: django-basic-config
Version: 1.1.0
Summary: This is a basic django app that creates a table for EAV (Entity-Attribute-Value) configuration settings.
Home-page: https://github.com/jonathanmorgan/django_config
Author: Jonathan Morgan
Author-email: jonathan.morgan.007@gmail.com
License: UNKNOWN
Platform: UNKNOWN
Classifier: Programming Language :: Python :: 3
Classifier: License :: OSI Approved :: GNU Lesser General Public License v3 or later (LGPLv3+)
Classifier: Operating System :: OS Independent
Classifier: Development Status :: 5 - Production/Stable
Classifier: Framework :: Django
Classifier: Intended Audience :: Developers
Classifier: Intended Audience :: Science/Research
Classifier: Topic :: Utilities
Requires-Python: >=3.6
License-File: LICENSE
Requires-Dist: django
